contribution_writer/__init__.py
contribution_writer/__main__.py
contribution_writer/cli.py
contribution_writer/font.py
github_contribution_writer-1.0.0.dist-info/METADATA
github_contribution_writer-1.0.0.dist-info/WHEEL
github_contribution_writer-1.0.0.dist-info/entry_points.txt
github_contribution_writer-1.0.0.dist-info/top_level.txt
github_contribution_writer-1.0.0.dist-info/RECORD
