Metadata-Version: 2.4
Name: github-contribution-writer
Version: 1.0.0
Summary: Draw words on your GitHub contribution graph with backdated commits
Author-email: Dinesh <info@dineshd.dev>
License: MIT
Project-URL: Repository, https://github.com/dinesh-git17/github-contribution-writer
Project-URL: Documentation, https://github.com/dinesh-git17/github-contribution-writer#readme
Keywords: github,contributions,git,cli
Classifier: Development Status :: 4 - Beta
Classifier: Environment :: Console
Classifier: Intended Audience :: Developers
Classifier: License :: OSI Approved :: MIT License
Classifier: Programming Language :: Python :: 3
Classifier: Programming Language :: Python :: 3.10
Classifier: Programming Language :: Python :: 3.11
Classifier: Programming Language :: Python :: 3.12
Classifier: Topic :: Software Development :: Version Control :: Git
Requires-Python: >=3.10
